odoo9_addon_account_move_line_stock_info-9.0.1.0.0.99.dev11-py2.7-nspkg.pth
odoo9_addon_account_move_line_stock_info-9.0.1.0.0.99.dev11.dist-info/DESCRIPTION.rst
odoo9_addon_account_move_line_stock_info-9.0.1.0.0.99.dev11.dist-info/METADATA
odoo9_addon_account_move_line_stock_info-9.0.1.0.0.99.dev11.dist-info/RECORD
odoo9_addon_account_move_line_stock_info-9.0.1.0.0.99.dev11.dist-info/WHEEL
odoo9_addon_account_move_line_stock_info-9.0.1.0.0.99.dev11.dist-info/metadata.json
odoo9_addon_account_move_line_stock_info-9.0.1.0.0.99.dev11.dist-info/namespace_packages.txt
odoo9_addon_account_move_line_stock_info-9.0.1.0.0.99.dev11.dist-info/top_level.txt
odoo_addons/account_move_line_stock_info/README.rst
odoo_addons/account_move_line_stock_info/__init__.py
odoo_addons/account_move_line_stock_info/__openerp__.py
odoo_addons/account_move_line_stock_info/i18n/account_move_line_stock_info.pot
odoo_addons/account_move_line_stock_info/i18n/ar.po
odoo_addons/account_move_line_stock_info/i18n/bs.po
odoo_addons/account_move_line_stock_info/i18n/ca.po
odoo_addons/account_move_line_stock_info/i18n/cs.po
odoo_addons/account_move_line_stock_info/i18n/de.po
odoo_addons/account_move_line_stock_info/i18n/en_GB.po
odoo_addons/account_move_line_stock_info/i18n/es.po
odoo_addons/account_move_line_stock_info/i18n/es_AR.po
odoo_addons/account_move_line_stock_info/i18n/es_CR.po
odoo_addons/account_move_line_stock_info/i18n/es_EC.po
odoo_addons/account_move_line_stock_info/i18n/es_MX.po
odoo_addons/account_move_line_stock_info/i18n/fi.po
odoo_addons/account_move_line_stock_info/i18n/fr.po
odoo_addons/account_move_line_stock_info/i18n/fr_CH.po
odoo_addons/account_move_line_stock_info/i18n/gl.po
odoo_addons/account_move_line_stock_info/i18n/hr.po
odoo_addons/account_move_line_stock_info/i18n/hr_HR.po
odoo_addons/account_move_line_stock_info/i18n/hu.po
odoo_addons/account_move_line_stock_info/i18n/id.po
odoo_addons/account_move_line_stock_info/i18n/it.po
odoo_addons/account_move_line_stock_info/i18n/ja.po
odoo_addons/account_move_line_stock_info/i18n/lt.po
odoo_addons/account_move_line_stock_info/i18n/mk.po
odoo_addons/account_move_line_stock_info/i18n/mn.po
odoo_addons/account_move_line_stock_info/i18n/nb.po
odoo_addons/account_move_line_stock_info/i18n/nb_NO.po
odoo_addons/account_move_line_stock_info/i18n/nl.po
odoo_addons/account_move_line_stock_info/i18n/nl_BE.po
odoo_addons/account_move_line_stock_info/i18n/pt.po
odoo_addons/account_move_line_stock_info/i18n/pt_BR.po
odoo_addons/account_move_line_stock_info/i18n/pt_PT.po
