Metadata-Version: 2.0
Name: odoo9-addon-account-move-line-stock-info
Version: 9.0.1.0.0.99.dev11
Summary: Account Move Line Stock Move
Home-page: https://github.com/OCA/stock-logistics-warehouse
Author: Eficent,Odoo Community Association (OCA)
Author-email: support@odoo-community.org
License: AGPL-3
Platform: UNKNOWN
Classifier: Programming Language :: Python
Classifier: Framework :: Odoo
Classifier: License :: OSI Approved :: GNU Affero General Public License v3
Requires-Python: ~=2.7
Requires-Dist: odoo (<9.1a,>=9.0a)
